README.rst
setup.cfg
setup.py
acme/__init__.py
acme/hello.py
acme.hello.egg-info/PKG-INFO
acme.hello.egg-info/SOURCES.txt
acme.hello.egg-info/dependency_links.txt
acme.hello.egg-info/namespace_packages.txt
acme.hello.egg-info/top_level.txt